jupyterlab_colourful_tab_extension/__init__.py
jupyterlab_colourful_tab_extension/_version.py
jupyterlab_colourful_tab_extension/tests/__init__.py
jupyterlab_colourful_tab_extension/tests/test_extension.py
jupyterlab_colourful_tab_extension-1.0.18.data/data/share/jupyter/labextensions/jupyterlab_colourful_tab_extension/package.json
jupyterlab_colourful_tab_extension-1.0.18.data/data/share/jupyter/labextensions/jupyterlab_colourful_tab_extension/schemas/jupyterlab_colourful_tab_extension/package.json.orig
jupyterlab_colourful_tab_extension-1.0.18.data/data/share/jupyter/labextensions/jupyterlab_colourful_tab_extension/schemas/jupyterlab_colourful_tab_extension/plugin.json
jupyterlab_colourful_tab_extension-1.0.18.data/data/share/jupyter/labextensions/jupyterlab_colourful_tab_extension/static/509.fcbdb91f53f5712e44b5.js
jupyterlab_colourful_tab_extension-1.0.18.data/data/share/jupyter/labextensions/jupyterlab_colourful_tab_extension/static/728.0196b13c602db5db2187.js
jupyterlab_colourful_tab_extension-1.0.18.data/data/share/jupyter/labextensions/jupyterlab_colourful_tab_extension/static/remoteEntry.8527a99dcd281332f8c5.js
jupyterlab_colourful_tab_extension-1.0.18.data/data/share/jupyter/labextensions/jupyterlab_colourful_tab_extension/static/style.js
jupyterlab_colourful_tab_extension-1.0.18.data/data/share/jupyter/labextensions/jupyterlab_colourful_tab_extension/static/third-party-licenses.json
jupyterlab_colourful_tab_extension-1.0.18.data/data/share/jupyter/labextensions/jupyterlab_colourful_tab_extension/install.json
jupyterlab_colourful_tab_extension-1.0.18.dist-info/METADATA
jupyterlab_colourful_tab_extension-1.0.18.dist-info/WHEEL
jupyterlab_colourful_tab_extension-1.0.18.dist-info/licenses/LICENSE
jupyterlab_colourful_tab_extension-1.0.18.dist-info/RECORD
